client/__init__.py
client/api_client.py
client/app.py
client/config.py
client/theme.py
client/version.py
client/screens/__init__.py
client/screens/game_screen.py
client/screens/help_screen.py
client/screens/leaderboard_screen.py
client/screens/login_screen.py
client/screens/result_screen.py
client/screens/settings_screen.py
client/screens/stats_screen.py
client/widgets/__init__.py
client/widgets/contribution_graph.py
client/widgets/game_board.py
client/widgets/keyboard.py
client/widgets/stats_panel.py
client/widgets/tile.py
data/answer_words_offline.txt
data/valid_words.txt
data/words_offline.json
server/__init__.py
server/config.py
server/database.py
server/main.py
server/admin/__init__.py
server/admin/router.py
server/admin/dist/favicon.svg
server/admin/dist/index.html
server/admin/dist/assets/Dashboard-Bt_ns6Rr.js
server/admin/dist/assets/Dashboard-naijFLvM.css
server/admin/dist/assets/Leaderboard-CX4amZlr.css
server/admin/dist/assets/Leaderboard-DODwOf6q.js
server/admin/dist/assets/Users-BTlVaFg0.js
server/admin/dist/assets/Users-Bsucqxof.css
server/admin/dist/assets/Words-CnwcHI65.js
server/admin/dist/assets/Words-zIA4-nhp.css
server/admin/dist/assets/index-DGjkZJYb.css
server/admin/dist/assets/index-DbvbEOKI.js
server/admin/static/dashboard.html
server/auth/__init__.py
server/auth/dependencies.py
server/auth/models.py
server/auth/router.py
server/auth/schemas.py
server/auth/service.py
server/games/__init__.py
server/games/models.py
server/games/router.py
server/games/schemas.py
server/games/service.py
server/leaderboard/__init__.py
server/leaderboard/router.py
server/leaderboard/schemas.py
server/leaderboard/service.py
server/stats/__init__.py
server/stats/router.py
server/stats/schemas.py
server/stats/service.py
server/streaks/__init__.py
server/streaks/models.py
server/streaks/router.py
server/streaks/schemas.py
server/streaks/service.py
server/words/__init__.py
server/words/models.py
server/words/router.py
server/words/schemas.py
server/words/service.py
tui_wordle-0.1.3.dist-info/METADATA
tui_wordle-0.1.3.dist-info/WHEEL
tui_wordle-0.1.3.dist-info/entry_points.txt
tui_wordle-0.1.3.dist-info/licenses/LICENSE
tui_wordle-0.1.3.dist-info/RECORD
